<?xml version="1.0" encoding="utf-8"?>
<Law xmlns:xsi="http://www.w3.org/2001/XMLSchema-instance" xmlns:xsd="http://www.w3.org/2001/XMLSchema" Id="478">
  <Title>Reconnaissance officielle de la religion catholique comme religion d'état</Title>
  <Description>Jésus est mort pour nos péchés. C'est un fait. La laïcité n'a mené nul part et le pays ne s'est jamais aussi bien porté que lorsqu'il avait une religion pour tous. Remettons ca.</Description>
  <YesPropertyModifiers>
    <PropertyModifier AttributeName="GOVERNMENTOPINION" Value="0" />
    <PropertyModifier AttributeName="POPULACEOPINION" Value="-10" />
    <PropertyModifier AttributeName="ECONOMY" Value="0" />
    <PropertyModifier AttributeName="EMPLOYMENT" Value="0" />
    <PropertyModifier AttributeName="RELIGION" Value="25" />
    <PropertyModifier AttributeName="PERSONALMONEY" Value="30000" />
  </YesPropertyModifiers>
  <YesLawsToAdd>
    <LawId>145</LawId>
  </YesLawsToAdd>
  <NoPropertyModifiers>
    <PropertyModifier AttributeName="GOVERNMENTOPINION" Value="-4" />
    <PropertyModifier AttributeName="POPULACEOPINION" Value="13" />
    <PropertyModifier AttributeName="ECONOMY" Value="0" />
    <PropertyModifier AttributeName="EMPLOYMENT" Value="0" />
    <PropertyModifier AttributeName="RELIGION" Value="-20" />
    <PropertyModifier AttributeName="PERSONALMONEY" Value="0" />
  </NoPropertyModifiers>
  <NoLawsToAdd />
  <MinimizePropertyModifiers />
  <MinimizeLawsToAdd>
    <LawId>-1</LawId>
  </MinimizeLawsToAdd>
  <MaximizePropertyModifiers />
  <MaximizeLawsToAdd>
    <LawId>-1</LawId>
  </MaximizeLawsToAdd>
</Law>