<?xml version="1.0" encoding="utf-8"?>
<Law xmlns:xsi="http://www.w3.org/2001/XMLSchema-instance" xmlns:xsd="http://www.w3.org/2001/XMLSchema" Id="161">
  <Title>Légalisation de l'euthanasie</Title>
  <Description />
  <YesPropertyModifiers>
    <PropertyModifier AttributeName="GOVERNMENTOPINION" Value="0" />
    <PropertyModifier AttributeName="POPULACEOPINION" Value="10" />
    <PropertyModifier AttributeName="ECONOMY" Value="-5" />
    <PropertyModifier AttributeName="EMPLOYMENT" Value="5" />
    <PropertyModifier AttributeName="RELIGION" Value="-20" />
  </YesPropertyModifiers>
  <YesLawsToAdd>
    <LawId>162</LawId>
  </YesLawsToAdd>
  <NoPropertyModifiers>
    <PropertyModifier AttributeName="GOVERNMENTOPINION" Value="5" />
    <PropertyModifier AttributeName="POPULACEOPINION" Value="-10" />
    <PropertyModifier AttributeName="ECONOMY" Value="0" />
    <PropertyModifier AttributeName="EMPLOYMENT" Value="0" />
    <PropertyModifier AttributeName="RELIGION" Value="10" />
  </NoPropertyModifiers>
  <NoLawsToAdd />
  <MinimizePropertyModifiers />
  <MinimizeLawsToAdd>
    <LawId>328</LawId>
  </MinimizeLawsToAdd>
  <MaximizePropertyModifiers />
  <MaximizeLawsToAdd>
    <LawId>495</LawId>
  </MaximizeLawsToAdd>
</Law>