<?xml version="1.0" encoding="utf-8"?>
<Law xmlns:xsi="http://www.w3.org/2001/XMLSchema-instance" xmlns:xsd="http://www.w3.org/2001/XMLSchema" Id="20">
  <Title>Reconnaissance de la pénibilité du travail</Title>
  <Description>Mise en place d'une retraite anticipée pour les métiers à risque (5 ans plus tôt que pour les autres). Une mesure humaine selon les humains, honteuse selon les employeurs.</Description>
  <YesPropertyModifiers>
    <PropertyModifier AttributeName="GOVERNMENTOPINION" Value="-8" />
    <PropertyModifier AttributeName="POPULACEOPINION" Value="5" />
    <PropertyModifier AttributeName="ECONOMY" Value="-5" />
    <PropertyModifier AttributeName="EMPLOYMENT" Value="5" />
    <PropertyModifier AttributeName="RELIGION" Value="0" />
    <PropertyModifier AttributeName="PERSONALMONEY" Value="0" />
  </YesPropertyModifiers>
  <YesLawsToAdd />
  <NoPropertyModifiers>
    <PropertyModifier AttributeName="GOVERNMENTOPINION" Value="3" />
    <PropertyModifier AttributeName="POPULACEOPINION" Value="0" />
    <PropertyModifier AttributeName="ECONOMY" Value="5" />
    <PropertyModifier AttributeName="EMPLOYMENT" Value="5" />
    <PropertyModifier AttributeName="RELIGION" Value="0" />
    <PropertyModifier AttributeName="PERSONALMONEY" Value="5000" />
  </NoPropertyModifiers>
  <NoLawsToAdd />
  <MinimizePropertyModifiers />
  <MinimizeLawsToAdd>
    <LawId>187</LawId>
  </MinimizeLawsToAdd>
  <MaximizePropertyModifiers />
  <MaximizeLawsToAdd>
    <LawId>354</LawId>
  </MaximizeLawsToAdd>
</Law>